setup.cfg
setup.py
twisting/__init__.py
twisting/messages.py
twisting/progress_base.py
twisting/progress_info.py
twisting/progress_interface.py
twisting/progress_manager.py
twisting/task_base.py
twisting/task_interface.py
twisting/tools.py
twisting.egg-info/PKG-INFO
twisting.egg-info/SOURCES.txt
twisting.egg-info/dependency_links.txt
twisting.egg-info/not-zip-safe
twisting.egg-info/requires.txt
twisting.egg-info/top_level.txt
twisting/gui_worker/__init__.py
twisting/gui_worker/progressbox.py
twisting/gui_worker/progresswindow.py
twisting/gui_worker/taskbox.py
twisting/tests/__init__.py
twisting/tests/test_base_worker.py
twisting/worker/__init__.py
twisting/worker/progress.py
twisting/worker/task.py