Metadata-Version: 1.0
Name: twisting
Version: 0.6.3
Summary: twisting is based on twisted deferred thread with GTK
Home-page: http://bitbucket.org/florent/twisting
Author: Florent PIGOUT
Author-email: florent.pigout@gmail.com
License: BSD
Platform: UNKNOWN
